cerebraai/__init__.py
cerebraai/algorithms/__init__.py
cerebraai/algorithms/analysis.py
cerebraai/algorithms/semantic.py
cerebraai/algorithms/sentiment.py
cerebraai/algorithms/topic.py
cerebraai/algorithms/utils.py
cerebraai/models/__init__.py
cerebraai/models/llm.py
cerebraai/models/orchestrator.py
cerebraai-0.2.3.dist-info/licenses/LICENSE
cerebraai-0.2.3.dist-info/METADATA
cerebraai-0.2.3.dist-info/WHEEL
cerebraai-0.2.3.dist-info/top_level.txt
cerebraai-0.2.3.dist-info/RECORD
