Metadata-Version: 2.4
Name: cerebraai
Version: 0.2.3
Summary: Cerebra is an AI Orchestrator for LLM models.
Author: Juan Pablo Gutiérrez
Author-email: <58833781+jpgtzg@users.noreply.github.com>
Keywords: python,video,stream,video stream,camera stream,sockets
Classifier: Development Status :: 2 - Pre-Alpha
Classifier: Intended Audience :: Developers
Classifier: Programming Language :: Python :: 3
Classifier: Operating System :: Unix
Classifier: Operating System :: MacOS :: MacOS X
Classifier: Operating System :: Microsoft :: Windows
License-File: LICENSE
Requires-Dist: annotated-types>=0.7.0
Requires-Dist: anyio>=4.8.0
Requires-Dist: backports.tarfile>=1.2.0
Requires-Dist: build>=1.2.2.post1
Requires-Dist: CacheControl>=0.14.2
Requires-Dist: certifi>=2024.12.14
Requires-Dist: cffi>=1.17.1
Requires-Dist: charset-normalizer>=3.4.1
Requires-Dist: cleo>=2.1.0
Requires-Dist: click>=8.1.8
Requires-Dist: contourpy>=1.3.1
Requires-Dist: crashtest>=0.4.1
Requires-Dist: cycler>=0.12.1
Requires-Dist: distlib>=0.3.9
Requires-Dist: distro>=1.9.0
Requires-Dist: dulwich>=0.22.7
Requires-Dist: emoji>=1.7.0
Requires-Dist: exceptiongroup>=1.2.2
Requires-Dist: fastjsonschema>=2.21.1
Requires-Dist: filelock>=3.16.1
Requires-Dist: fonttools>=4.55.3
Requires-Dist: fsspec>=2024.12.0
Requires-Dist: h11>=0.14.0
Requires-Dist: httpcore>=1.0.7
Requires-Dist: httpx>=0.28.1
Requires-Dist: huggingface-hub>=0.27.0
Requires-Dist: idna>=3.10
Requires-Dist: importlib_metadata>=8.5.0
Requires-Dist: installer>=0.7.0
Requires-Dist: jaraco.classes>=3.4.0
Requires-Dist: jaraco.context>=6.0.1
Requires-Dist: jaraco.functools>=4.1.0
Requires-Dist: Jinja2>=3.1.5
Requires-Dist: jiter>=0.8.2
Requires-Dist: joblib>=1.4.2
Requires-Dist: keyring>=25.6.0
Requires-Dist: kiwisolver>=1.4.8
Requires-Dist: MarkupSafe>=3.0.2
Requires-Dist: matplotlib>=3.10.0
Requires-Dist: more-itertools>=10.5.0
Requires-Dist: mpmath>=1.3.0
Requires-Dist: msgpack>=1.1.0
Requires-Dist: networkx>=3.4.2
Requires-Dist: nltk>=3.5
Requires-Dist: numpy>=2.2.1
Requires-Dist: packaging>=24.2
Requires-Dist: pillow>=11.1.0
Requires-Dist: pkginfo>=1.12.0
Requires-Dist: platformdirs>=4.3.6
Requires-Dist: poetry>=2.0.0
Requires-Dist: poetry-core>=2.0.0
Requires-Dist: pycparser>=2.22
Requires-Dist: pydantic>=2.10.4
Requires-Dist: pydantic_core>=2.27.2
Requires-Dist: pyparsing>=3.2.1
Requires-Dist: pyproject_hooks>=1.2.0
Requires-Dist: python-dateutil>=2.9.0.post0
Requires-Dist: python-dotenv>=1.0.1
Requires-Dist: PyYAML>=6.0.2
Requires-Dist: RapidFuzz>=3.11.0
Requires-Dist: regex>=2024.11.6
Requires-Dist: requests>=2.32.3
Requires-Dist: requests-toolbelt>=1.0.0
Requires-Dist: safetensors>=0.5.0
Requires-Dist: scikit-fuzzy>=0.5.0
Requires-Dist: scikit-learn>=1.6.0
Requires-Dist: scipy>=1.15.0
Requires-Dist: sentence-transformers>=3.3.1
Requires-Dist: shellingham>=1.5.4
Requires-Dist: six>=1.17.0
Requires-Dist: sniffio>=1.3.1
Requires-Dist: sympy>=1.13.1
Requires-Dist: text2emotion>=0.0.5
Requires-Dist: threadpoolctl>=3.5.0
Requires-Dist: tiktoken>=0.8.0
Requires-Dist: tokenizers>=0.21.0
Requires-Dist: tomli>=2.2.1
Requires-Dist: tomlkit>=0.13.2
Requires-Dist: torch>=2.5.1
Requires-Dist: tqdm>=4.67.1
Requires-Dist: transformers>=4.47.1
Requires-Dist: trove-classifiers>=2025.1.7.14
Requires-Dist: typing_extensions>=4.12.2
Requires-Dist: urllib3>=2.3.0
Requires-Dist: virtualenv>=20.28.1
Requires-Dist: xattr>=1.1.4
Requires-Dist: zipp>=3.21.0
Dynamic: author
Dynamic: author-email
Dynamic: classifier
Dynamic: keywords
Dynamic: license-file
Dynamic: requires-dist
Dynamic: summary
